tewl/__init__.py
tewl/context.py
tewl/foo.py
tewl-0.0.1.dist-info/LICENSE
tewl-0.0.1.dist-info/WHEEL
tewl-0.0.1.dist-info/METADATA
tewl-0.0.1.dist-info/RECORD
