Metadata-Version: 2.1
Name: tewl
Version: 0.0.1
Summary: Kewl tools for Python
Home-page: https://github.com/kristjanvalur/py-tewl
Author: Kristján Valur Jónsson
Author-email: fsweskman@gmail.com
Requires-Python: >=3.8,<3.11
Classifier: Programming Language :: Python :: 3
Classifier: Programming Language :: Python :: 3.10
Classifier: Programming Language :: Python :: 3.8
Classifier: Programming Language :: Python :: 3.9
Project-URL: Documentation, https://kristjanvalur.github.io/py-tewl/
Project-URL: Repository, https://github.com/kristjanvalur/py-tewl
